rustipy/__init__.py
rustipy/option.py
rustipy/py.typed
rustipy/result.py
rustipy-0.2.1.dist-info/WHEEL
rustipy-0.2.1.dist-info/METADATA
rustipy-0.2.1.dist-info/RECORD
