Metadata-Version: 2.3
Name: rustipy
Version: 0.2.1
Summary: Rustipy your python project
Author: Siyoung September
Author-email: Siyoung September <loldruger@gmail.com>
Requires-Dist: pytest>=9.0.2 ; extra == 'dev'
Requires-Dist: ruff>=0.14.13 ; extra == 'dev'
Requires-Dist: ty>=0.0.12 ; extra == 'dev'
Requires-Python: >=3.13
Provides-Extra: dev
